btform-0.1.dist-info/metadata.json
btform-0.1.dist-info/zip-safe
btform-0.1.dist-info/WHEEL
btform-0.1.dist-info/METADATA
btform-0.1.dist-info/DESCRIPTION.rst
btform-0.1.dist-info/RECORD
btform-0.1.dist-info/top_level.txt
btform/__init__.py
btform/net.py
btform/dataform.py
btform/rules.py
