Metadata-Version: 2.0
Name: btform
Version: 0.1
Summary: web app forms tools
Home-page: https://github.com/talkincode/btform
Author: jamiesun
Author-email: jamiesun.net@gmail.com
License: MIT
Keywords: web,form,html,http
Platform: UNKNOWN
Classifier: Development Status :: 6 - Mature
Classifier: Intended Audience :: Developers
Classifier: Programming Language :: Python :: 2.6
Classifier: Programming Language :: Python :: 2.7
Classifier: Topic :: Software Development :: Libraries :: Python Modules
Classifier: Topic :: Internet :: WWW/HTTP
